ayga_mcp_client/__init__.py
ayga_mcp_client/__main__.py
ayga_mcp_client/error_handler.py
ayga_mcp_client/health_monitor.py
ayga_mcp_client/server.py
ayga_mcp_client/api/__init__.py
ayga_mcp_client/api/client.py
ayga_mcp_client-1.4.1.dist-info/LICENSE
ayga_mcp_client-1.4.1.dist-info/METADATA
ayga_mcp_client-1.4.1.dist-info/WHEEL
ayga_mcp_client-1.4.1.dist-info/entry_points.txt
ayga_mcp_client-1.4.1.dist-info/top_level.txt
ayga_mcp_client-1.4.1.dist-info/RECORD
