Metadata-Version: 2.1
Name: ayga-mcp-client
Version: 1.4.1
Summary: MCP server for Redis API with 40 AI parsers across 9 categories (Perplexity, ChatGPT, Instagram, TikTok, Google Trends, Pinterest, Link Extractor, YouTube, Translation, Search Engines)
Author-email: Ozan D <support@ayga.tech>
License: MIT
Project-URL: Homepage, https://github.com/ozand/ayga-mcp-client
Project-URL: Documentation, https://redis.ayga.tech/docs
Project-URL: Repository, https://github.com/ozand/ayga-mcp-client
Project-URL: Issues, https://github.com/ozand/ayga-mcp-client/issues
Keywords: mcp,redis,ai,parsers,claude,copilot,perplexity,chatgpt
Classifier: Development Status :: 4 - Beta
Classifier: Intended Audience :: Developers
Classifier: Programming Language :: Python :: 3.11
Classifier: Programming Language :: Python :: 3.12
Classifier: Topic :: Software Development :: Libraries
Classifier: Topic :: Scientific/Engineering :: Artificial Intelligence
Requires-Python: >=3.11
License-File: LICENSE
Requires-Dist: mcp>=1.0.0
Requires-Dist: httpx>=0.27.0
Requires-Dist: pydantic>=2.0.0
Provides-Extra: dev
Requires-Dist: pytest>=8.0.0; extra == "dev"
Requires-Dist: pytest-asyncio>=0.24.0; extra == "dev"
Requires-Dist: ruff>=0.6.0; extra == "dev"
Requires-Dist: mypy>=1.11.0; extra == "dev"
